missing_python/missing_values.py
missing_values_yash_saxena-1.0.2.dist-info/LICENSE
missing_values_yash_saxena-1.0.2.dist-info/METADATA
missing_values_yash_saxena-1.0.2.dist-info/WHEEL
missing_values_yash_saxena-1.0.2.dist-info/entry_points.txt
missing_values_yash_saxena-1.0.2.dist-info/top_level.txt
missing_values_yash_saxena-1.0.2.dist-info/RECORD
